{
  "pipeline_execution": {
    "start_time": "2025-07-27T00:14:07.932886",
    "end_time": "2025-07-27T00:14:16.758647",
    "total_execution_time": "0:00:08.825761",
    "status": {
      "data_update": {
        "status": "success",
        "execution_time": "0:00:00.435897",
        "timestamp": "2025-07-27T00:14:08.368783"
      },
      "adaptive_analysis": {
        "status": "success",
        "execution_time": "0:00:00.026429",
        "timestamp": "2025-07-27T00:14:08.395212"
      },
      "weight_optimization": {
        "status": "success",
        "execution_time": "0:00:00.008866",
        "timestamp": "2025-07-27T00:14:08.404078"
      },
      "prediction_generation": {
        "status": "success",
        "execution_time": "0:00:06.195297",
        "timestamp": "2025-07-27T00:14:14.599375"
      },
      "historical_validation": {
        "status": "success",
        "execution_time": "0:00:02.150362",
        "timestamp": "2025-07-27T00:14:16.750739"
      },
      "performance_analysis": {
        "status": "success",
        "execution_time": "0:00:00.006434",
        "timestamp": "2025-07-27T00:14:16.757173"
      }
    }
  },
  "system_info": {
    "config_file": "config/config.ini",
    "historical_data_records": 2205,
    "adaptive_system_initialized": true
  },
  "generated_at": "2025-07-27T00:14:16.758647"
}