{
  "pipeline_execution": {
    "start_time": "2025-08-07T19:50:28.866114",
    "end_time": "2025-08-07T19:52:57.827513",
    "total_execution_time": "0:02:28.961402",
    "status": {
      "data_update": {
        "status": "success",
        "execution_time": "0:00:00.462963",
        "timestamp": "2025-08-07T19:50:29.329403"
      },
      "adaptive_analysis": {
        "status": "success",
        "execution_time": "0:00:00.009846",
        "timestamp": "2025-08-07T19:50:29.339522"
      },
      "weight_optimization": {
        "status": "success",
        "execution_time": "0:00:00.019373",
        "timestamp": "2025-08-07T19:50:29.359182"
      },
      "historical_validation": {
        "status": "success",
        "execution_time": "0:00:00.023628",
        "timestamp": "2025-08-07T19:50:29.383080"
      },
      "prediction_generation": {
        "status": "success",
        "execution_time": "0:02:28.440096",
        "timestamp": "2025-08-07T19:52:57.823478"
      },
      "performance_analysis": {
        "status": "success",
        "execution_time": "0:00:00.003315",
        "timestamp": "2025-08-07T19:52:57.827080"
      }
    }
  },
  "system_info": {
    "config_file": "config/config.ini",
    "historical_data_records": 2210,
    "adaptive_system_initialized": true
  },
  "generated_at": "2025-08-07T19:52:57.827532"
}