{
  "pipeline_execution": {
    "start_time": "2025-08-06T12:31:27.567060",
    "end_time": "2025-08-06T12:34:19.438592",
    "total_execution_time": "0:02:51.871536",
    "status": {
      "data_update": {
        "status": "success",
        "execution_time": "0:00:00.510646",
        "timestamp": "2025-08-06T12:31:28.077865"
      },
      "adaptive_analysis": {
        "status": "success",
        "execution_time": "0:00:00.010802",
        "timestamp": "2025-08-06T12:31:28.088985"
      },
      "prediction_generation": {
        "status": "success",
        "execution_time": "0:02:51.275667",
        "timestamp": "2025-08-06T12:34:19.364982"
      },
      "weight_optimization": {
        "status": "success",
        "execution_time": "0:00:00.001694",
        "timestamp": "2025-08-06T12:34:19.367047"
      },
      "historical_validation": {
        "status": "success",
        "execution_time": "0:00:00.066047",
        "timestamp": "2025-08-06T12:34:19.433356"
      },
      "performance_analysis": {
        "status": "success",
        "execution_time": "0:00:00.004602",
        "timestamp": "2025-08-06T12:34:19.438240"
      }
    }
  },
  "system_info": {
    "config_file": "config/config.ini",
    "historical_data_records": 2209,
    "adaptive_system_initialized": true
  },
  "generated_at": "2025-08-06T12:34:19.438615"
}